zebconf/__init__.py
zebconf/__main__.py
zebconf/cli.py
zebconf/connection.py
zebconf/device.py
zebconf/firmware.py
zebconf/logging.py
zebconf/tests/__init__.py
zebconf/tests/test01_basic.py
zebconf-0.1.9.dist-info/COPYING
zebconf-0.1.9.dist-info/METADATA
zebconf-0.1.9.dist-info/WHEEL
zebconf-0.1.9.dist-info/entry_points.txt
zebconf-0.1.9.dist-info/top_level.txt
zebconf-0.1.9.dist-info/RECORD
