Metadata-Version: 2.1
Name: zebconf
Version: 0.1.9
Summary: Zebra printer configuration
Home-page: https://github.com/unipartdigital/zebconf
Author: Michael Brown
Author-email: mbrown@fensystems.co.uk
License: GPLv2+
Platform: UNKNOWN
Classifier: Development Status :: 3 - Alpha
Classifier: Environment :: Console
Classifier: Intended Audience :: System Administrators
Classifier: License :: OSI Approved :: GNU General Public License v2 or later (GPLv2+)
Classifier: Programming Language :: Python :: 3
Classifier: Topic :: Printing
Requires-Dist: future
Requires-Dist: passlib
Requires-Dist: pyusb
